[{"df":2,"postings":"data/search/postings/5d.json","token":"5-dichloro-2-octyl-2h-isothiazol-3-one"},{"df":3,"postings":"data/search/postings/5d.json","token":"5-dichlorobenzoic"},{"df":1,"postings":"data/search/postings/5d.json","token":"5-dien-2-one"},{"df":1,"postings":"data/search/postings/5d.json","token":"5-dihydrooxazol-2-amine"},{"df":2,"postings":"data/search/postings/5d.json","token":"5-dimethoxy-n"},{"df":1,"postings":"data/search/postings/5d.json","token":"5-dimethyl"},{"df":1,"postings":"data/search/postings/5d.json","token":"5-dimethyl-1"},{"df":1,"postings":"data/search/postings/5d.json","token":"5-dimethylphenol"},{"df":2,"postings":"data/search/postings/5d.json","token":"5-dimethylthiophene"},{"df":1,"postings":"data/search/postings/5d.json","token":"5-dithiazine"},{"df":3,"postings":"data/search/postings/5d.json","token":"5d"},{"df":1,"postings":"data/search/postings/5d.json","token":"5dt"},{"df":4,"postings":"data/search/postings/5d.json","token":"5du"}]
