{
  "nde": [
    {
      "df": 1,
      "token": "ndeveloper"
    }
  ],
  "ndev": [
    {
      "df": 1,
      "token": "ndeveloper"
    }
  ],
  "ndeve": [
    {
      "df": 1,
      "token": "ndeveloper"
    }
  ],
  "ndevel": [
    {
      "df": 1,
      "token": "ndeveloper"
    }
  ],
  "ndevelo": [
    {
      "df": 1,
      "token": "ndeveloper"
    }
  ],
  "ndevelop": [
    {
      "df": 1,
      "token": "ndeveloper"
    }
  ],
  "ndo": [
    {
      "df": 1,
      "token": "ndop"
    }
  ],
  "ndop": [
    {
      "df": 1,
      "token": "ndop"
    }
  ]
}
