{"nig":[{"df":3,"token":"night"},{"df":1,"token":"nightly"}],"nigh":[{"df":3,"token":"night"},{"df":1,"token":"nightly"}],"night":[{"df":3,"token":"night"},{"df":1,"token":"nightly"}],"nightl":[{"df":1,"token":"nightly"}],"nightly":[{"df":1,"token":"nightly"}],"nin":[{"df":11,"token":"nine"}],"nine":[{"df":11,"token":"nine"}],"nit":[{"df":21,"token":"nitrogen"}],"nitr":[{"df":21,"token":"nitrogen"}],"nitro":[{"df":21,"token":"nitrogen"}],"nitrog":[{"df":21,"token":"nitrogen"}],"nitroge":[{"df":21,"token":"nitrogen"}],"nitrogen":[{"df":21,"token":"nitrogen"}]}
